pcpy/__init__.py
pcpy/catalog.json
pcpy/constants.py
pcpy/operation.py
pcpy/pcset.py
pcpy/query.py
pcpy/relation.py
pcpy-0.1.0.dist-info/LICENSE.md
pcpy-0.1.0.dist-info/METADATA
pcpy-0.1.0.dist-info/WHEEL
pcpy-0.1.0.dist-info/RECORD
