Metadata-Version: 2.1
Name: pcpy
Version: 0.1.0
Summary: A Python package for pc set operations, relation measures, and queries.
Home-page: https://github.com/programsounds/pcpy
License: MIT
Author: Yota Kobayashi
Author-email: yota@programsounds.net
Requires-Python: >=3.9,<4.0
Classifier: License :: OSI Approved :: MIT License
Classifier: Programming Language :: Python :: 3
Classifier: Programming Language :: Python :: 3.9
Classifier: Programming Language :: Python :: 3.10
Classifier: Programming Language :: Python :: 3.11
Project-URL: Repository, https://github.com/programsounds/pcpy
